manchats.py
manchats-1.dist-info/METADATA
manchats-1.dist-info/WHEEL
manchats-1.dist-info/top_level.txt
manchats-1.dist-info/RECORD
